sinterp/__init__.py
sinterp/config.py
sinterp/helpers.py
sinterp/sinterp.py
sinterp-0.2.0.dist-info/LICENSE
sinterp-0.2.0.dist-info/METADATA
sinterp-0.2.0.dist-info/WHEEL
sinterp-0.2.0.dist-info/top_level.txt
sinterp-0.2.0.dist-info/RECORD
