Metadata-Version: 2.1
Name: sinterp
Version: 0.2.0
Summary: Simple fast linear interpolation for Python
Home-page: https://github.com/ndrwpvlv/sinterp
Author: Andrei S. Pavlov
Author-email: ndrw.pvlv@gmail.com
License: MIT
Download-URL: https://github.com/ndrwpvlv/sinterp/archive/0.2.0.tar.gz
Keywords: interpolation,linear interpolation
Platform: UNKNOWN
Classifier: Programming Language :: Python :: 3.5
Classifier: Programming Language :: Python :: 3.6
Classifier: Programming Language :: Python :: 3.7
Classifier: Programming Language :: Python :: 3.8
Classifier: Programming Language :: Python :: 3.9
Classifier: Operating System :: OS Independent
Classifier: License :: OSI Approved :: MIT License
License-File: LICENSE
Requires-Dist: attrs (==21.2.0)
Requires-Dist: importlib-metadata (==4.5.0)
Requires-Dist: iniconfig (==1.1.1)
Requires-Dist: packaging (==20.9)
Requires-Dist: pluggy (==0.13.1)
Requires-Dist: py (==1.10.0)
Requires-Dist: pyparsing (==2.4.7)
Requires-Dist: pytest (==6.2.4)
Requires-Dist: toml (==0.10.2)
Requires-Dist: typing-extensions (==3.10.0.0)
Requires-Dist: zipp (==3.4.1)
